gampy/__init__.py
gampy/advices.py
gampy/errors.py
gampy/structures.py
gampy-1.1.0.dist-info/LICENSE.txt
gampy-1.1.0.dist-info/METADATA
gampy-1.1.0.dist-info/WHEEL
gampy-1.1.0.dist-info/entry_points.txt
gampy-1.1.0.dist-info/top_level.txt
gampy-1.1.0.dist-info/RECORD
