Metadata-Version: 2.1
Name: gampy
Version: 1.1.0
Summary: General Abstract Meta Programming for Python
Home-page: https://github.com/fmind/gampy
Author: Médéric Hurier (fmind)
Author-email: fmind@fmind.me
License: LGPL-3.0
Keywords: general abstract meta programming
Platform: UNKNOWN
Classifier: Development Status :: 4 - Beta
Requires-Python: >=3.7
